mtpynux/__init__.py
mtpynux/__main__.py
mtpynux-1.0.8.dist-info/LICENSE.txt
mtpynux-1.0.8.dist-info/METADATA
mtpynux-1.0.8.dist-info/WHEEL
mtpynux-1.0.8.dist-info/top_level.txt
mtpynux-1.0.8.dist-info/RECORD
