Metadata-Version: 2.1
Name: mtpynux
Version: 1.0.8
Summary: METATRADER PYTHON LINUX
Home-page: https://github.com/pythonsystem/mtpynux
Author: Lucas Campagna
License: MIT
License-File: LICENSE.txt
Requires-Dist: pyparsing ==3.1.2
Requires-Dist: rpyc ==5.2.3
Requires-Dist: plumbum ==1.7.0
Requires-Dist: numpy ==1.24.3
